<?xml version="1.0" encoding="utf-8"?>
<translations xmlns="http://xaraya.com/2002/ns/translations" locale="hu_HU.utf-8">
<entry><string>Static Text</string><translation>Statikus szöveg</translation></entry>
<entry><string>Text Box</string><translation>Egysoros szöveg</translation></entry>
<entry><string>Small Text Area</string><translation>Kis szövegmező</translation></entry>
<entry><string>Medium Text Area</string><translation>Közepes szövegmező</translation></entry>
<entry><string>Large Text Area</string><translation>Nagy szövegmező</translation></entry>
<entry><string>Dropdown List</string><translation>Lenyíló lista</translation></entry>
<entry><string>Text Upload</string><translation>Szöveg feltöltő</translation></entry>
<entry><string>File Upload</string><translation>Fájl feltöltő</translation></entry>
<entry><string>URL</string><translation>URL</translation></entry>
<entry><string>URL + Title</string><translation>URL + Cím</translation></entry>
<entry><string>Image List</string><translation>Képlista</translation></entry>
<entry><string>Calendar</string><translation>Naptár</translation></entry>
<entry><string>HTML Page</string><translation>HTML oldal</translation></entry>
<entry><string>Username</string><translation>Felhasználónév</translation></entry>
<entry><string>User List</string><translation>Felhasználó lista</translation></entry>
<entry><string>Language List</string><translation>Nyelv lista</translation></entry>
<entry><string>xarTinyMCE GUI</string><translation>TinyMCE szerkesztő</translation></entry>
</translations>
