<?xml version="1.0" encoding="utf-8"?>
<translations xmlns="http://xaraya.com/2002/ns/translations" locale="sv_SE.utf-8">
<entry><string>Go to Home Webpage</string><translation>Gå till hem webbsidan</translation></entry>
<entry><string>View Contact Webpage</string><translation>Visa kontakt webbsidan</translation></entry>
<entry><string>View Legal Terms</string><translation>Visa juridiska villkor</translation></entry>
<entry><string>View Privacy Statement</string><translation>Visa integritetspolicy</translation></entry>
<entry><string>Home</string><translation>Hem</translation></entry>
<entry><string>Contact Us</string><translation>Kontakta oss</translation></entry>
<entry><string>Legal</string><translation>Villkor</translation></entry>
<entry><string>Privacy</string><translation>Integritet</translation></entry>
</translations>
