<?xml version="1.0" encoding="utf-8"?>
<translations xmlns="http://xaraya.com/2002/ns/translations" locale="fi_FI.utf-8">
<entry><string>Themes</string><translation>Teemat</translation></entry>
<entry><string>Activate</string><translation></translation></entry>
<entry><string>Deactivate</string><translation></translation></entry>
<entry><string>Upgrade</string><translation></translation></entry>
<entry><string>Remove</string><translation></translation></entry>
<entry><string>Themes Administration</string><translation></translation></entry>
<entry><string>View Themes</string><translation></translation></entry>
<entry><string>Action</string><translation></translation></entry>
<entry><string>Refresh</string><translation></translation></entry>
<entry><string>Name</string><translation></translation></entry>
<entry><string>Version</string><translation></translation></entry>
<entry><string>Actions</string><translation></translation></entry>
<entry><string>Info</string><translation></translation></entry>
<entry><string>Overview</string><translation></translation></entry>
<entry><string>Template Tags</string><translation></translation></entry>
<entry><string>Modify Config</string><translation></translation></entry>
<entry><string>Delete</string><translation></translation></entry>
<entry><string>Description:</string><translation></translation></entry>
<entry><string>Select Theme</string><translation></translation></entry>
<entry><string>Edit</string><translation></translation></entry>
<entry><string>Submit</string><translation></translation></entry>
<entry><string>All</string><translation></translation></entry>
<entry><string>None</string><translation></translation></entry>
<entry><string>Could not unregister (#(1)).</string><translation></translation></entry>
<entry><string>Empty regid (#(1)).</string><translation></translation></entry>
<entry><string>Missing theme regid (#(1)).</string><translation></translation></entry>
<entry><string>Parameter filter must be an array.</string><translation></translation></entry>
<entry><string>Parameter orderBy can contain only 'name' or 'regid' or 'class' as items.</string><translation></translation></entry>
<entry><string>Unable to activate module &quot;#(1)&quot;.</string><translation></translation></entry>
</translations>
