<?xml version="1.0" encoding="utf-8"?>
<translations xmlns="http://xaraya.com/2002/ns/translations" locale="de_DE.utf-8">
<entry><string>Invalid value for config variable: barscale</string><translation>Ungültiger Wert für Konfigurationsvariable: barscale</translation></entry>
<entry><string>Invalid value for config variable: defaultopts</string><translation>Ungültiger Wert für Konfigurationsvariable: defaultopts</translation></entry>
<entry><string>Invalid value for config variable: imggraph</string><translation>Ungültiger Wert für Konfigurationsvariable: imggraph</translation></entry>
<entry><string>Invalid value for config variable: voteinterval</string><translation>Ungültiger Wert für Konfigurationsvariable: voteinterval</translation></entry>
</translations>
