<?xml version="1.0" encoding="utf-8"?>
<translations xmlns="http://xaraya.com/2002/ns/translations" locale="de_DE.utf-8">
<entry><string>Existing Poll List</string><translation>Liste existierender Umfragen</translation></entry>
<entry><string>Choose polls status</string><translation>Umfragestatus wählen</translation></entry>
<entry><string>Status</string><translation>Status</translation></entry>
<entry><string>opened</string><translation>geöffnet</translation></entry>
<entry><string>upcoming</string><translation>kommend</translation></entry>
<entry><string>closed</string><translation>geschlossen</translation></entry>
<entry><string>all</string><translation>alle</translation></entry>
<entry><string>Type</string><translation>Typ</translation></entry>
<entry><string>Hooked</string><translation>Hooked</translation></entry>
<entry><string>Close</string><translation>Beenden</translation></entry>
<entry><string>Reset</string><translation>Zurücksetzen</translation></entry>
</translations>
