<?xml version="1.0" encoding="utf-8"?>
<translations xmlns="http://xaraya.com/2002/ns/translations" locale="fi_FI.utf-8">
<entry><string>Courses</string><translation></translation></entry>
<entry><string>Invalid #(1) for #(2) function #(3)() in module #(4)</string><translation></translation></entry>
<entry><string>Confirm</string><translation></translation></entry>
<entry><string>Item ID</string><translation></translation></entry>
<entry><string>ID of course occurence</string><translation></translation></entry>
<entry><string>Cancel</string><translation></translation></entry>
<entry><string>Add Course</string><translation></translation></entry>
<entry><string>Course Name</string><translation></translation></entry>
<entry><string>Course Number</string><translation></translation></entry>
<entry><string>Course Level</string><translation></translation></entry>
<entry><string>Year for this occurence</string><translation></translation></entry>
<entry><string>Course Credits</string><translation></translation></entry>
<entry><string>Start date</string><translation></translation></entry>
<entry><string>End date</string><translation></translation></entry>
<entry><string>Course Fee</string><translation></translation></entry>
<entry><string>Course materials</string><translation></translation></entry>
<entry><string>Course Maximum Credits</string><translation></translation></entry>
<entry><string>Course Prerequisites</string><translation></translation></entry>
<entry><string>Course Aim</string><translation></translation></entry>
<entry><string>Course coordinators</string><translation></translation></entry>
<entry><string>Course committee</string><translation></translation></entry>
<entry><string>Course lecturers</string><translation></translation></entry>
<entry><string>Course location</string><translation></translation></entry>
<entry><string>Course Language</string><translation></translation></entry>
<entry><string>Course Frequency</string><translation></translation></entry>
<entry><string>Course Contact details</string><translation></translation></entry>
<entry><string>Minimum Participants</string><translation></translation></entry>
<entry><string>Maximum Participants</string><translation></translation></entry>
<entry><string>Registration closing date</string><translation></translation></entry>
<entry><string>Hide this occurence</string><translation></translation></entry>
<entry><string>E-mail address</string><translation></translation></entry>
<entry><string>Options</string><translation></translation></entry>
<entry><string>Edit</string><translation></translation></entry>
<entry><string>Delete</string><translation></translation></entry>
<entry><string>View Courses</string><translation></translation></entry>
<entry><string>Course types</string><translation></translation></entry>
<entry><string>Courses Administration</string><translation></translation></entry>
<entry><string>Overview</string><translation></translation></entry>
<entry><string>Preview</string><translation></translation></entry>
<entry><string>Hooked content</string><translation></translation></entry>
<entry><string>Display</string><translation></translation></entry>
<entry><string>Modify</string><translation></translation></entry>
<entry><string>Course general details</string><translation></translation></entry>
<entry><string>The code/number of this course.</string><translation></translation></entry>
<entry><string>Course Code</string><translation></translation></entry>
<entry><string>The Frequency of this course.</string><translation></translation></entry>
<entry><string>Course contents</string><translation></translation></entry>
<entry><string>Description</string><translation></translation></entry>
<entry><string>The level of this course</string><translation></translation></entry>
<entry><string>Level</string><translation></translation></entry>
<entry><string>The credits that in general will be given for this course.</string><translation></translation></entry>
<entry><string>Intended credits</string><translation></translation></entry>
<entry><string>Period</string><translation></translation></entry>
<entry><string>Location</string><translation></translation></entry>
<entry><string>Credits</string><translation></translation></entry>
<entry><string>Expected #(1)</string><translation></translation></entry>
<entry><string>Short Course Description</string><translation></translation></entry>
<entry><string>The ID of this occurence of the course.</string><translation></translation></entry>
<entry><string>Name and numbering</string><translation></translation></entry>
<entry><string>Enter the name for this course.</string><translation></translation></entry>
<entry><string>ERROR! This is not a valid name</string><translation></translation></entry>
<entry><string>ERROR! This name already exists</string><translation></translation></entry>
<entry><string>ERROR! This is not a valid course number</string><translation></translation></entry>
<entry><string>ERROR! This course number already exists</string><translation></translation></entry>
<entry><string>Enter the type of course.</string><translation></translation></entry>
<entry><string>Course Type</string><translation></translation></entry>
<entry><string>Enter the level of this course.</string><translation></translation></entry>
<entry><string>Additional information</string><translation></translation></entry>
<entry><string>Enter short description for this course.</string><translation></translation></entry>
<entry><string>ERROR! This is not a valid course description</string><translation></translation></entry>
<entry><string>Enter the frequency for this course.</string><translation></translation></entry>
<entry><string>ERROR! This is not a valid frequency</string><translation></translation></entry>
<entry><string>Enter detailed contact information for this course.</string><translation></translation></entry>
<entry><string>Hide this course from being viewed by site users.</string><translation></translation></entry>
<entry><string>Hide Course</string><translation></translation></entry>
<entry><string>ERROR! This is not possible</string><translation></translation></entry>
<entry><string>Date of last modification.</string><translation></translation></entry>
<entry><string>The name of this course.</string><translation></translation></entry>
<entry><string>Choose the course year or period for this occurence.</string><translation></translation></entry>
<entry><string>The date this course will start.</string><translation></translation></entry>
<entry><string>ERROR! This is not a valid startdate for this course.</string><translation></translation></entry>
<entry><string>The date this course will end.</string><translation></translation></entry>
<entry><string>ERROR! This is not a valid ending date for this course.</string><translation></translation></entry>
<entry><string>The date registration for this course will end.</string><translation></translation></entry>
<entry><string>If there is text in this field, the course will be shown as expected.</string><translation></translation></entry>
<entry><string>Expected: (Optional)</string><translation></translation></entry>
<entry><string>ERROR! This is not a valid expected description</string><translation></translation></entry>
<entry><string>Course credits</string><translation></translation></entry>
<entry><string>Enter the number of credits for this course.</string><translation></translation></entry>
<entry><string>ERROR! This is not a valid amount of credits</string><translation></translation></entry>
<entry><string>Enter the minimum amount of credits for this course.</string><translation></translation></entry>
<entry><string>ERROR! This is not a valid amount of minimum credits</string><translation></translation></entry>
<entry><string>Enter the maximum amount of credits for this course.</string><translation></translation></entry>
<entry><string>ERROR! This is not a valid amount of maximum credits</string><translation></translation></entry>
<entry><string>Enter the prerequisites (Like another course to fulfill before a student can enroll into this one) for this course.</string><translation></translation></entry>
<entry><string>ERROR! This is not a prerequisites type</string><translation></translation></entry>
<entry><string>Enter the aim of this course.</string><translation></translation></entry>
<entry><string>ERROR! This is not a valid aim type</string><translation></translation></entry>
<entry><string>Enter a complete description for this course, supplementing the short description.</string><translation></translation></entry>
<entry><string>Long Course Description</string><translation></translation></entry>
<entry><string>ERROR! This is not a valid long decription</string><translation></translation></entry>
<entry><string>The programme of this course.</string><translation></translation></entry>
<entry><string>ERROR! This is not a valid programme description</string><translation></translation></entry>
<entry><string>Describe the methods used in this course.</string><translation></translation></entry>
<entry><string>Course Method</string><translation></translation></entry>
<entry><string>ERROR! This is not a valid method description</string><translation></translation></entry>
<entry><string>The lecturers for this course.</string><translation></translation></entry>
<entry><string>ERROR! This is not a valid lecturers description</string><translation></translation></entry>
<entry><string>Course conditions</string><translation></translation></entry>
<entry><string>The costs to enroll into this course.</string><translation></translation></entry>
<entry><string>ERROR! This is not a valid cost</string><translation></translation></entry>
<entry><string>The minimum amount of students that should enroll in this course.</string><translation></translation></entry>
<entry><string>The maximum amount of students that can enroll in this course.</string><translation></translation></entry>
<entry><string>The material used in this course.</string><translation></translation></entry>
<entry><string>The location of this course.</string><translation></translation></entry>
<entry><string>ERROR! This is not a valid location</string><translation></translation></entry>
<entry><string>The coordinators for this course.</string><translation></translation></entry>
<entry><string>ERROR! This is not a valid coordinators description</string><translation></translation></entry>
<entry><string>The organising committee for this course.</string><translation></translation></entry>
<entry><string>ERROR! This is not a valid committee description</string><translation></translation></entry>
<entry><string>Others</string><translation></translation></entry>
<entry><string>Other info on this course.</string><translation></translation></entry>
<entry><string>ERROR! This is not a valid info description</string><translation></translation></entry>
<entry><string>When checked, a user is redirected to the URL below when he enrolls in a course.</string><translation></translation></entry>
<entry><string>Use external registration</string><translation></translation></entry>
<entry><string>The URL to redirect to when external registration is used.</string><translation></translation></entry>
<entry><string>External Registration URL</string><translation></translation></entry>
<entry><string>ERROR! This is not a valid regurl description</string><translation></translation></entry>
<entry><string>Hide this planning from being viewed by site users.</string><translation></translation></entry>
<entry><string>Course Title</string><translation></translation></entry>
<entry><string>Type ID</string><translation></translation></entry>
<entry><string>Course Programme</string><translation></translation></entry>
<entry><string>Other Course info</string><translation></translation></entry>
<entry><string>Date last modified</string><translation></translation></entry>
<entry><string>Registration Closed</string><translation></translation></entry>
<entry><string>Title</string><translation></translation></entry>
<entry><string>Participants</string><translation></translation></entry>
<entry><string>Dear #(1),</string><translation></translation></entry>
<entry><string>Name of the course:</string><translation></translation></entry>
<entry><string>Code of the course:</string><translation></translation></entry>
<entry><string>Link to the course:</string><translation></translation></entry>
<entry><string>This course will start on:</string><translation></translation></entry>
<entry><string>This course is expected:</string><translation></translation></entry>
<entry><string>Link to all your courses:</string><translation></translation></entry>
<entry><string>Dear</string><translation></translation></entry>
<entry><string>which starts on</string><translation></translation></entry>
<entry><string>which is expected</string><translation></translation></entry>
<entry><string>This is the course type description</string><translation></translation></entry>
<entry><string>ERROR! This is not a valid courses description</string><translation></translation></entry>
<entry><string>ERROR! This is not a valid courses type</string><translation></translation></entry>
<entry><string>Course</string><translation></translation></entry>
<entry><string>Enrolled</string><translation></translation></entry>
<entry><string>Enroll</string><translation></translation></entry>
<entry><string>This course does not exists</string><translation></translation></entry>
<entry><string>Enter the number of courses to display.</string><translation></translation></entry>
<entry><string>Number of Items</string><translation></translation></entry>
</translations>
