<?xml version="1.0" encoding="utf-8"?>
<translations xmlns="http://xaraya.com/2002/ns/translations" locale="el_GR.utf-8">
<entry><string>The same registered ID (#(1)) was found in two different modules, #(2) and #(3). Please remove one of the modules and regenerate the list.</string><translation>Το ίδιο καταχωρημένο ID (#(1)) βρέθηκε σε δύο διαφορετικές μονάδες, #(2) και #(3). Αφαιρέστε την μία από τις δύο μονάδας και ξανεπιχειρήστε αναγέννηση της λίστας</translation></entry>
<entry><string>The module #(1) was found under two different registered IDs, #(2) and #(3). Please remove one of the modules and regenerate the list</string><translation>Η μονάδα #(1) βρέθηκε με δύο διαφορετικά ID, #(2) και #(3). Αφαιρέστε την μία από τις δύο μονάδας και ξανεπιχειρήστε αναγέννηση της λίστας</translation></entry>
</translations>
