<?xml version="1.0" encoding="utf-8"?>
<translations xmlns="http://xaraya.com/2002/ns/translations" locale="hu_HU.utf-8">
<entry><string>Dear</string><translation>Kedves</translation></entry>
<entry><string>A user registered with the following details at:</string><translation>Új felhasználó regisztrált:</translation></entry>
<entry><string>User Display Name:</string><translation>Megjelenített név:</translation></entry>
<entry><string>User email:</string><translation>E-mail cím:</translation></entry>
</translations>
