<?xml version="1.0" encoding="utf-8"?>
<translations xmlns="http://xaraya.com/2002/ns/translations" locale="fi_FI.utf-8">
<entry><string>Xaraya Help System</string><translation>Xarayan Ohjejärjestelmä</translation></entry>
<entry><string>Help File Not Found</string><translation>Ohjetiedostoa ei löydy</translation></entry>
<entry><string>There is no help information for this Xaraya extension.</string><translation>Tälle Xarayan laajennukselle ei ole ohjetta.</translation></entry>
<entry><string>The Xaraya help system is not fully implemented at this stage.
Most links display an existing extension Overview. This link will be replaced in the near future by a
global Help system.</string><translation>Xarayan Ohjejärjestelmä ei ole tällä hetkellä täysin valmis. Useimmat linkit näyttävät kyseisen laajennuksen Yleiskatsauksen. Tämä linkki korvataan lähitulevaisuudessa koko järjestelmän kattavalla Ohjejärjestelmällä.</translation></entry>
<entry><string>You can report a missing Overview file by lodging a bug report at</string><translation>Voit ilmoittaa puuttuvasta Yleiskatsauksesta tekemällä vikailmoituksen osoitteessa</translation></entry>
<entry><string>If you are interested in helping to write an Overview for a module
see</string><translation>Jos haluat auttaa kirjoittamalla itse Yleiskatsauksen moduulille, voit tarkastella tiedostoa</translation></entry>
<entry><string>as an example.</string><translation>esimerkkinä.</translation></entry>
</translations>
