<?xml version="1.0" encoding="utf-8"?>
<translations xmlns="http://xaraya.com/2002/ns/translations" locale="de_DE.utf-8">
<entry><string>Add or Edit Pubblication</string><translation>Publikation hinzufügen oder bearbeiten</translation></entry>
<entry><string>Name of the Pubblication</string><translation>Name der Publikation</translation></entry>
<entry><string>Choose:</string><translation>Wählen:</translation></entry>
<entry><string>Next</string><translation>Weiter</translation></entry>
<entry><string>You must add a publication before creating a new issue.</string><translation>Sie müssen erst eine Publikation hinzufügen, bevor Sie eine neue Ausgabe anlegen können.</translation></entry>
<entry><string>Create a New Publication</string><translation>Eine neue Publikation anlegen</translation></entry>
</translations>
