<?xml version="1.0" encoding="utf-8"?>
<translations xmlns="http://xaraya.com/2002/ns/translations" locale="de_DE.utf-8">
<entry><string>Click on a tab to display specific information from your server php installation</string><translation>Anklicken, um spezifische Informationen der serverseitigen PHP-Installation anzeigen zu lassen</translation></entry>
<entry><string>PHP Information:</string><translation>PHP-Information:</translation></entry>
<entry><string>General info</string><translation>Allgemeine Informationen</translation></entry>
<entry><string>Credits</string><translation>Mitwirkende (Credits)</translation></entry>
<entry><string>Configuration</string><translation>Konfiguration</translation></entry>
<entry><string>Environment</string><translation>Umfeld (Environment)</translation></entry>
<entry><string>Variables</string><translation>Variablen</translation></entry>
<entry><string>License</string><translation>Lizenz</translation></entry>
<entry><string>All</string><translation>Alles</translation></entry>
</translations>
