<?xml version="1.0" encoding="utf-8"?>
<translations xmlns="http://xaraya.com/2002/ns/translations" locale="hu_HU.utf-8">
<entry><string>Module Settings and Hooks</string><translation>Modul beállítások és hurkok</translation></entry>
<entry><string>For Module:</string><translation>A következő modulhoz:</translation></entry>
<entry><string>Enter new display name (Does not work)</string><translation>Új megjelenítési név megadása (még nem működik)</translation></entry>
<entry><string>No hooks available for #(1)</string><translation>A(z) #(1) modulhoz nincsenek hurkok.</translation></entry>
<entry><string>Available hooks for #(1):</string><translation>Hurkok a(z) #(1) modulhoz:</translation></entry>
<entry><string>Hooks from module:</string><translation>Hurkok a következő modulból:</translation></entry>
<entry><string>Enable hooks for:</string><translation>Hurok bekapcsolása:</translation></entry>
<entry><string>All</string><translation>Összes</translation></entry>
<entry><string>Available hooks:</string><translation>Elérhető hurkok:</translation></entry>
</translations>
