<?xml version="1.0" encoding="utf-8"?>
<translations xmlns="http://xaraya.com/2002/ns/translations" locale="de_DE.utf-8">
<entry><string>Category relationship hiearchy.</string><translation>Bezugspunkt für die nachstehende Positionierung</translation></entry>
<entry><string>In relation to this category</string><translation>Bezugskategorie</translation></entry>
<entry><string>Position of this category.</string><translation>Zielposition dieser Kategorie.</translation></entry>
<entry><string>Position</string><translation>Position</translation></entry>
<entry><string>Right before, in the same level</string><translation>Vor der Bezugskategorie, gleichrangig</translation></entry>
<entry><string>Right after, in the same level</string><translation>Hinter der Bezugskategorie, gleichrangig</translation></entry>
<entry><string>The first child category</string><translation>Erste Unterkategorie der Bezugskategorie</translation></entry>
<entry><string>The last child category</string><translation>Letzte Unterkategorie der Bezugskategorie</translation></entry>
</translations>
