<?xml version="1.0" encoding="utf-8"?>
<translations xmlns="http://xaraya.com/2002/ns/translations" locale="el_GR.utf-8">
<entry><string>Newsgroups</string><translation>Newsgroups</translation></entry>
<entry><string>Select Newsgroups</string><translation>Επιλογή Newsgroups</translation></entry>
<entry><string>Modify Config</string><translation>Τροποποίηση Ρυθμίσεων</translation></entry>
<entry><string>Invalid newsgroup</string><translation>Άκυρο newsgroup</translation></entry>
<entry><string>Overview</string><translation>Περίληψη</translation></entry>
<entry><string>NewsGroups Administration</string><translation>Διαχείριση NewsGroups</translation></entry>
<entry><string>Wildcard Match</string><translation>Ταίριασμα Wildcard</translation></entry>
<entry><string>News Server Error:</string><translation>Σφάλμα Εξυπηρετητή News:</translation></entry>
<entry><string>Subject</string><translation>Θέμα</translation></entry>
<entry><string>From</string><translation>Από</translation></entry>
<entry><string>Date</string><translation>Ημερομηνία</translation></entry>
</translations>
