<?xml version="1.0" encoding="utf-8"?>
<translations xmlns="http://xaraya.com/2002/ns/translations" locale="hu_HU.utf-8">
<entry><string>Recipient Name.</string><translation>A címzett neve.</translation></entry>
<entry><string>Recipient Email Address.</string><translation>A címzett e-mail címe.</translation></entry>
<entry><string>Email:</string><translation>E-mail:</translation></entry>
<entry><string>Recipient CC.</string><translation>A másolat címzettjének e-mail címe.</translation></entry>
<entry><string>CC:</string><translation>Másolat e-mail cím:</translation></entry>
<entry><string>CC Name.</string><translation>A másolat címzettjének neve.</translation></entry>
<entry><string>CC Name:</string><translation>Másolat név:</translation></entry>
<entry><string>Recipient BCC.</string><translation>A titkos másolat címzettjének e-mail címe.</translation></entry>
<entry><string>BCC:</string><translation>Titkos másolat e-mail cím:</translation></entry>
<entry><string>BCC Name.</string><translation>A titkos másolat címzettjének neve.</translation></entry>
<entry><string>BCC Name:</string><translation>Titkos másolat név:</translation></entry>
<entry><string>Message Subject.</string><translation>Üzenet tárgya.</translation></entry>
<entry><string>Test scheduled mails.</string><translation>Időzített levélküldés ellenőrzése.</translation></entry>
<entry><string>No Earlier Than:</string><translation>Nem korábban mint:</translation></entry>
<entry><string>Send Test Message</string><translation>Próba üzenet elküldése</translation></entry>
</translations>
