<?xml version="1.0" encoding="utf-8"?>
<translations xmlns="http://xaraya.com/2002/ns/translations" locale="hu_HU.utf-8">
<entry><string>View Change Log Items for Editor #(1)</string><translation>#(1) szerkesztő változtatásainak megjelenítése</translation></entry>
<entry><string>View Change Log Items</string><translation>Változatok megjelenítése</translation></entry>
<entry><string>&lt;strong&gt;Module Name&lt;/strong&gt;</string><translation>&lt;strong&gt;Modul neve&lt;/strong&gt;</translation></entry>
<entry><string>&lt;strong&gt;Module Items&lt;/strong&gt;</string><translation>&lt;strong&gt;Modul elemek&lt;/strong&gt;</translation></entry>
<entry><string>&lt;strong&gt;Total Changes&lt;/strong&gt;</string><translation>&lt;strong&gt;Változások összesen&lt;/strong&gt;</translation></entry>
<entry><string>&lt;strong&gt;Action&lt;/strong&gt;</string><translation>&lt;strong&gt;Művelet&lt;/strong&gt;</translation></entry>
<entry><string>There are currently no changes in the database...</string><translation>Nincsenek változási bejegyzések az adatbázisban...</translation></entry>
<entry><string>Delete</string><translation>Törlés</translation></entry>
<entry><string>Grand Total</string><translation>Összesen</translation></entry>
<entry><string>Delete All</string><translation>Összes törlése</translation></entry>
<entry><string>Click on &lt;strong&gt;Delete&lt;/strong&gt; to delete &lt;strong&gt;all&lt;/strong&gt; changes
associated with a module. Click on a &lt;strong&gt;module name&lt;/strong&gt; to go to the module's statistics page. This page
contains the figures for all of the module's items that have changes associated with them.
You can delete all changes associated with a particular item from this page.</string><translation>A &lt;strong&gt;Törlés&lt;/strong&gt; megnyomásával törölhető az összes bejegyzés amely egy adott modulhoz tartozik. A &lt;strong&gt;modul nevén&lt;/strong&gt; történő kattintás az adott modul statisztikai oldalára vezet, ahol megjelennek az adott modul elemeihez tartozó változási bejegyzések. Innen törölhetőek az egyes elemekhez tartozó változási bejegyzések.</translation></entry>
<entry><string>Module #(1)</string><translation>Modul: #(1)</translation></entry>
<entry><string>&lt;strong&gt;Item Id&lt;/strong&gt;</string><translation>&lt;strong&gt;Elem azonosító&lt;/strong&gt;</translation></entry>
<entry><string>&lt;strong&gt;Changes&lt;/strong&gt;</string><translation>&lt;strong&gt;Változások&lt;/strong&gt;</translation></entry>
<entry><string>There are currently no changes attached to this module...</string><translation>Jelenleg ehhez a modulhoz nem tartoznak változások.</translation></entry>
<entry><string>View Log</string><translation>Napló megtekintése</translation></entry>
<entry><string>Click on &lt;strong&gt;View Log&lt;/strong&gt; to see all changes associated with a particular
module's item. &lt;br /&gt;
Click on &lt;strong&gt;Delete&lt;/strong&gt; to delete all changes for a module item.&lt;br /&gt;
Click on &lt;strong&gt;Item Name&lt;/strong&gt; to view the item.</string><translation>A &lt;strong&gt;Napló megtekintése&lt;/strong&gt; lehetőséget biztosít egy adott modul adott eleméhez tartozó változási bejegyzések megtekintésére, és ezek törlésére a &lt;b&gt;Törlés&lt;/b&gt; kiválasztásával.&lt;br /&gt;Az &lt;strong&gt;elem nevén&lt;/strong&gt; kattitva megjeleníthető az adott elem.</translation></entry>
</translations>
