<?xml version="1.0" encoding="utf-8"?>
<translations xmlns="http://xaraya.com/2002/ns/translations" locale="nl_NL.utf-8">
<entry><string>Confirm deleting this course</string><translation></translation></entry>
<entry><string>This course has been planned #(1) times. You can only delete courses that are not planned, otherwise you will introduce data errors in the database.</string><translation></translation></entry>
<entry><string>You can however not show it to your users by hiding it.
Use the button below to go to the modify page.</string><translation></translation></entry>
<entry><string>Modify this course</string><translation></translation></entry>
</translations>
